docker_tabcomplete/__init__.py
docker_tabcomplete/parser.py
docker_tabcomplete/queries.py
xontrib/docker_tabcomplete.xsh
xonsh_docker_tabcomplete-0.1.5.dist-info/LICENSE
xonsh_docker_tabcomplete-0.1.5.dist-info/METADATA
xonsh_docker_tabcomplete-0.1.5.dist-info/WHEEL
xonsh_docker_tabcomplete-0.1.5.dist-info/top_level.txt
xonsh_docker_tabcomplete-0.1.5.dist-info/RECORD
